ruslanio/__init__.py
ruslanio/arrays.py
ruslanio/batched.py
ruslanio/beam_search.py
ruslanio/cacher.py
ruslanio/fast_heapq.py
ruslanio/image.py
ruslanio/sorting.py
ruslanio-0.1.2.dist-info/LICENSE
ruslanio-0.1.2.dist-info/METADATA
ruslanio-0.1.2.dist-info/WHEEL
ruslanio-0.1.2.dist-info/top_level.txt
ruslanio-0.1.2.dist-info/RECORD
