Metadata-Version: 2.1
Name: ruslanio
Version: 0.1.2
Summary: My personal tools for my projects
Home-page: https://github.com/hocop/ruslanio
Author: Ruslan Baynazarov
Author-email: 
License: WTFPL
License-File: LICENSE
Requires-Dist: numpy
Requires-Dist: opencv-python
Requires-Dist: tqdm
Requires-Dist: msgspec
Requires-Dist: redis ==5.0.1
